{
  "db_name": "PostgreSQL",
  "query": "\n            SELECT\n                id, username, email, password_hash, display_name,\n                auth_provider as \"auth_provider: AuthProvider\",\n                external_id, is_admin, is_active, must_change_password,\n                last_login_at, created_at, updated_at\n            FROM users\n            WHERE username = $1 AND is_active = true\n            ",
  "describe": {
    "columns": [
      {
        "ordinal": 0,
        "name": "id",
        "type_info": "Uuid"
      },
      {
        "ordinal": 1,
        "name": "username",
        "type_info": "Varchar"
      },
      {
        "ordinal": 2,
        "name": "email",
        "type_info": "Varchar"
      },
      {
        "ordinal": 3,
        "name": "password_hash",
        "type_info": "Varchar"
      },
      {
        "ordinal": 4,
        "name": "display_name",
        "type_info": "Varchar"
      },
      {
        "ordinal": 5,
        "name": "auth_provider: AuthProvider",
        "type_info": {
          "Custom": {
            "name": "auth_provider",
            "kind": {
              "Enum": [
                "local",
                "ldap",
                "saml",
                "oidc"
              ]
            }
          }
        }
      },
      {
        "ordinal": 6,
        "name": "external_id",
        "type_info": "Varchar"
      },
      {
        "ordinal": 7,
        "name": "is_admin",
        "type_info": "Bool"
      },
      {
        "ordinal": 8,
        "name": "is_active",
        "type_info": "Bool"
      },
      {
        "ordinal": 9,
        "name": "must_change_password",
        "type_info": "Bool"
      },
      {
        "ordinal": 10,
        "name": "last_login_at",
        "type_info": "Timestamptz"
      },
      {
        "ordinal": 11,
        "name": "created_at",
        "type_info": "Timestamptz"
      },
      {
        "ordinal": 12,
        "name": "updated_at",
        "type_info": "Timestamptz"
      }
    ],
    "parameters": {
      "Left": [
        "Text"
      ]
    },
    "nullable": [
      false,
      false,
      false,
      true,
      true,
      false,
      true,
      false,
      false,
      false,
      true,
      false,
      false
    ]
  },
  "hash": "c7b26ffb0f2d7bd3ede70ebd00be3e06916d556edf8ec9c76928b87c723ccd04"
}
