{
  "db_name": "PostgreSQL",
  "query": "\n            UPDATE repositories\n            SET replication_priority = $2, updated_at = NOW()\n            WHERE id = $1\n            ",
  "describe": {
    "columns": [],
    "parameters": {
      "Left": [
        "Uuid",
        {
          "Custom": {
            "name": "replication_priority",
            "kind": {
              "Enum": [
                "immediate",
                "scheduled",
                "on_demand",
                "local_only"
              ]
            }
          }
        }
      ]
    },
    "nullable": []
  },
  "hash": "5ec2dc8d00eeb339068d1945ccefe48a76acd6c0959c4ad99301f381318afaa9"
}
